{"P4": {"labels": ["documentation"], "postTitle": "\u5982\u4f55\u7528AI\u8fdb\u884c\u5f15\u8a00\u7684\u6587\u732e\u67e5\u627e\u4e0e\u5339\u914d", "postUrl": "post/ru-he-yong-AI-jin-xing-yin-yan-de-wen-xian-cha-zhao-yu-pi-pei.html", "createdDate": "2026-07-16", "dateLabelColor": "#1f883d"}, "P3": {"labels": ["documentation"], "postTitle": "Obsidian\u91cc\u7684fast-note-sync\u914d\u7f6e\u6307\u5357", "postUrl": "post/Obsidian-li-de-fast-note-sync-pei-zhi-zhi-nan.html", "createdDate": "2026-07-16", "dateLabelColor": "#1f883d"}, "P2": {"labels": ["documentation"], "postTitle": "PDFMathTranslate\u548cpdf2zh\u5982\u4f55\u914d\u7f6e\u2014\u2014\u8bba\u6587\u9ad8\u7cbe\u5ea6\u7ffb\u8bd1\u6559\u7a0b", "postUrl": "post/PDFMathTranslate-he-pdf2zh-ru-he-pei-zhi-%E2%80%94%E2%80%94-lun-wen-gao-jing-du-fan-yi-jiao-cheng.html", "createdDate": "2026-07-16", "dateLabelColor": "#1f883d"}, "P1": {"labels": ["documentation"], "postTitle": "\u6559\u7a0b\u7bc7\u2014\u2014\u4f7f\u7528 PicGo + \u817e\u8baf\u4e91 COS \u56fe\u5e8a\u89e3\u51b3 Obsidian \u6587\u7ae0\u591a\u5e73\u53f0\u53d1\u5e03\u7684\u56fe\u7247\u95ee\u9898", "postUrl": "post/jiao-cheng-pian-%E2%80%94%E2%80%94-shi-yong-%20PicGo%20%2B%20-teng-xun-yun-%20COS%20-tu-chuang-jie-jue-%20Obsidian%20-wen-zhang-duo-ping-tai-fa-bu-de-tu-pian-wen-ti.html", "createdDate": "2026-07-16", "dateLabelColor": "#1f883d"}, "labelColorDict": {"bug": "#d73a4a", "documentation": "#0075ca", "duplicate": "#cfd3d7", "enhancement": "#a2eeef", "good first issue": "#7057ff", "help wanted": "#008672", "invalid": "#e4e669", "question": "#d876e3", "wontfix": "#ffffff"}}